ssdownload/__init__.py
ssdownload/cli.py
ssdownload/cli_utils.py
ssdownload/client.py
ssdownload/config.py
ssdownload/downloader.py
ssdownload/exceptions.py
ssdownload/filters.py
ssdownload/index_manager.py
ssdownload-0.1.0.dist-info/METADATA
ssdownload-0.1.0.dist-info/WHEEL
ssdownload-0.1.0.dist-info/entry_points.txt
ssdownload-0.1.0.dist-info/licenses/LICENSE
ssdownload-0.1.0.dist-info/RECORD
